infoml/__init__.py
infoml/binf/__init__.py
infoml/binf/data.py
infoml/data/GSE50499_GEO_Ceman_counts.txt.gz
infoml/data/__init__.py
infoml/data/boston-housing.txt.gz
infoml/datasets.py
infoml/pkg.py
infoml/utils.py
infoml/viz/__init__.py
infoml/viz/themes.py
infoml-0.8.0.dist-info/LICENSE
infoml-0.8.0.dist-info/WHEEL
infoml-0.8.0.dist-info/METADATA
infoml-0.8.0.dist-info/RECORD
