Metadata-Version: 2.1
Name: infoml
Version: 0.8.0
Summary: Python package for bioinformatics analysis and machine learning.
License: MIT
Author: Tony Kabilan Okeke
Requires-Python: >=3.10,<4.0
Classifier: License :: OSI Approved :: MIT License
Classifier: Programming Language :: Python :: 3
Classifier: Programming Language :: Python :: 3.10
Classifier: Programming Language :: Python :: 3.11
Requires-Dist: biopython (>=1.80,<2.0)
Requires-Dist: geoparse (>=2.0.3,<3.0.0)
Requires-Dist: numpy (>=1.22)
Requires-Dist: pandas (>=1.5.2,<2.0.0)
Requires-Dist: requests (>=2.28.1,<3.0.0)
Requires-Dist: rich (>=13.0.0,<14.0.0)
Requires-Dist: scikit-learn (>=1.2.0,<2.0.0)
Requires-Dist: scipy (>=1.9.3,<2.0.0)
Requires-Dist: seaborn (>=0.12.2,<0.13.0)
Requires-Dist: tqdm (>=4.64.1,<5.0.0)
